SmartLogs/__init__.py
SmartLogs/config.py
SmartLogs/debug.py
SmartLogs/formatter.py
SmartLogs/logger.py
smartlogs-1.1.0.dist-info/licenses/LICENSE
tests/__init__.py
tests/test_debug.py
tests/test_formatter.py
tests/test_logger.py
smartlogs-1.1.0.dist-info/METADATA
smartlogs-1.1.0.dist-info/WHEEL
smartlogs-1.1.0.dist-info/top_level.txt
smartlogs-1.1.0.dist-info/RECORD
