Metadata-Version: 2.4
Name: SmartLogs
Version: 1.1.0
Summary: 📢 Um logger inteligente para projetos Python, com suporte a cores, arquivos e integrações com Slack/Telegram.
Home-page: https://github.com/robertolima-dev/SmartLogs
Author: Roberto Lima
Author-email: Roberto Lima <robertolima.izphera@gmail.com>
License: MIT License
Project-URL: Source, https://github.com/robertolima-dev/SmartLogs
Project-URL: Tracker, https://github.com/robertolima-dev/SmartLogs/issues
Classifier: Programming Language :: Python :: 3
Classifier: License :: OSI Approved :: MIT License
Classifier: Operating System :: OS Independent
Requires-Python: >=3.6
License-File: LICENSE
Requires-Dist: colorama
Dynamic: author
Dynamic: home-page
Dynamic: license-file
Dynamic: requires-python
